samrand/__init__.py
samrand/reader.py
samrand/sampler.py
samrand-0.1.0.data/scripts/samrand
samrand-0.1.0.dist-info/LICENSE
samrand-0.1.0.dist-info/METADATA
samrand-0.1.0.dist-info/WHEEL
samrand-0.1.0.dist-info/top_level.txt
samrand-0.1.0.dist-info/RECORD
