Metadata-Version: 2.1
Name: samrand
Version: 0.1.0
Summary: A random sampling tool.
Home-page: https://gitlab.com/omazhary/SamRand
Author: omazhary
Author-email: omazhary@gmail.com
License: MIT
Keywords: data sample statistics
Platform: UNKNOWN
Classifier: Development Status :: 3 - Alpha
Classifier: Intended Audience :: Science/Research
Classifier: License :: OSI Approved :: MIT License
Classifier: Natural Language :: English
Classifier: Programming Language :: Python :: 3
Classifier: Topic :: Scientific/Engineering :: Information Analysis
Requires-Dist: argparse
Requires-Dist: numpy
